test
pounce
