Metadata-Version: 1.1
Name: Pounce
Version: 1.1
Summary: A simple CLI file downloader written for Python-3.x
Home-page: https://github.com/darthlukan/pounce.git
Author: Brian Tomlinson
Author-email: darthlukan@gmail.com
License: GPLv2
Download-URL: https://github.com/darthlukan/pounce.git
Platform: UNKNOWN
